trivia/__init__.py
trivia/__main__.py
trivia/base.py
trivia-0.1.0.dist-info/LICENSE
trivia-0.1.0.dist-info/METADATA
trivia-0.1.0.dist-info/WHEEL
trivia-0.1.0.dist-info/entry_points.txt
trivia-0.1.0.dist-info/top_level.txt
trivia-0.1.0.dist-info/RECORD
