Metadata-Version: 2.1
Name: trivia
Version: 0.1.0
Summary: Awesome trivia created by rochacbruno
Home-page: https://github.com/rochacbruno/trivia/
Author: rochacbruno
License: UNKNOWN
Platform: UNKNOWN
License-File: LICENSE
Requires-Dist: rich
Requires-Dist: textual
Requires-Dist: httpx
Provides-Extra: test
Requires-Dist: pytest ; extra == 'test'
Requires-Dist: coverage ; extra == 'test'
Requires-Dist: flake8 ; extra == 'test'
Requires-Dist: black ; extra == 'test'
Requires-Dist: isort ; extra == 'test'
Requires-Dist: pytest-cov ; extra == 'test'
Requires-Dist: codecov ; extra == 'test'
Requires-Dist: mypy ; extra == 'test'
Requires-Dist: gitchangelog ; extra == 'test'
Requires-Dist: mkdocs ; extra == 'test'
